pylogx/__init__.py
pylogx/levels.json
pylogx/log.py
pylogx-1.0.3.dist-info/LICENSE
pylogx-1.0.3.dist-info/METADATA
pylogx-1.0.3.dist-info/WHEEL
pylogx-1.0.3.dist-info/top_level.txt
pylogx-1.0.3.dist-info/RECORD
