Metadata-Version: 2.1
Name: pylogx
Version: 1.0.3
Summary: python logging extensions supporting additional levels, colorization and more
Author-email: Claudio Klingler <ck@realtime-projects.com>
Project-URL: Homepage, https://github.com/realtimeprojects/pylogx
Project-URL: Bug Tracker, https://github.com/realtimeprojects/pylogx/issues
Classifier: Programming Language :: Python :: 3
Classifier: License :: OSI Approved :: MIT License
Classifier: Operating System :: OS Independent
Requires-Python: >=3.7
License-File: LICENSE
Requires-Dist: termcolor
